MANIFEST.in
README.md
setup.py
iba2raystation.egg-info/PKG-INFO
iba2raystation.egg-info/SOURCES.txt
iba2raystation.egg-info/dependency_links.txt
iba2raystation.egg-info/entry_points.txt
iba2raystation.egg-info/requires.txt
iba2raystation.egg-info/top_level.txt
iba2rs/__init__.py
iba2rs/iba_to_python.py
iba2rs/iba_to_raystation.py
iba2rs/main.py