Metadata-Version: 1.1
Name: iba2raystation
Version: 0.1.4
Summary: Converts an IBA OmniPro Accept CSV into a RaySearch RayStation CSV
Home-page: https://github.com/cutright/IBA2RayStation
Author: Dan Cutright
Author-email: dan.cutright@gmail.com
License: MIT License
Download-URL: https://github.com/cutright/DVH-Analytics/archive/master.zip
Keywords: radiation therapy,beam commissioning
Platform: UNKNOWN
